djangocircle/__init__.py
djangocircle/django_cloud_logging/__init__.py
djangocircle/django_cloud_logging/log_middleware.py
djangocircle/django_cloud_logging/middleware.py
django_cloud_logging-0.1.0.dist-info/LICENSE
django_cloud_logging-0.1.0.dist-info/METADATA
django_cloud_logging-0.1.0.dist-info/WHEEL
django_cloud_logging-0.1.0.dist-info/top_level.txt
django_cloud_logging-0.1.0.dist-info/RECORD
