Metadata-Version: 2.1
Name: django-cloud-logging
Version: 0.1.0
Summary: A package which stores your django application logs in google stackdriver.
Home-page: UNKNOWN
Author: Django Circle
Author-email: djangocircle@gmail.com
License: UNKNOWN
Platform: UNKNOWN
Classifier: Programming Language :: Python :: 3
Classifier: License :: OSI Approved :: MIT License
Classifier: Operating System :: OS Independent
Requires-Python: >=3
Requires-Dist: django (>=2.2.12)
Requires-Dist: djangorestframework (>=3.11.0)
Requires-Dist: google-cloud-logging (>=1.15.0)
